todox/__init__.py
todox/cli.py
todox/gitutils.py
todox/models.py
todox/store.py
todox/tui.py
todox-0.1.2.dist-info/licenses/LICENSE
todox-0.1.2.dist-info/METADATA
todox-0.1.2.dist-info/WHEEL
todox-0.1.2.dist-info/entry_points.txt
todox-0.1.2.dist-info/top_level.txt
todox-0.1.2.dist-info/RECORD
