Metadata-Version: 2.4
Name: todox
Version: 0.1.2
Summary: A powerful, beautiful CLI + TUI todo application for developers who live in the terminal
Author-email: Sai Prasad Padhy <saiprasadpadhy@gmail.com>
Maintainer-email: Sai Prasad Padhy <saiprasadpadhy@gmail.com>
License: MIT
Project-URL: Homepage, https://github.com/padhysai/todox
Project-URL: Repository, https://github.com/padhysai/todox
Project-URL: Issues, https://github.com/padhysai/todox/issues
Project-URL: Changelog, https://github.com/padhysai/todox/blob/main/CHANGELOG.md
Keywords: todo,task-manager,cli,tui,terminal,productivity,developer-tools,task-list,command-line,textual,rich,git-integration,time-tracking,priority-management
Classifier: Development Status :: 4 - Beta
Classifier: Environment :: Console
Classifier: Intended Audience :: Developers
Classifier: License :: OSI Approved :: MIT License
Classifier: Operating System :: OS Independent
Classifier: Programming Language :: Python :: 3
Classifier: Programming Language :: Python :: 3.9
Classifier: Programming Language :: Python :: 3.10
Classifier: Programming Language :: Python :: 3.11
Classifier: Programming Language :: Python :: 3.12
Classifier: Topic :: Software Development
Classifier: Topic :: Utilities
Classifier: Topic :: Office/Business :: Scheduling
Classifier: Typing :: Typed
Requires-Python: >=3.9
License-File: LICENSE
Requires-Dist: typer>=0.9.0
Requires-Dist: textual>=0.40.0
Requires-Dist: rich>=13.0.0
Requires-Dist: rapidfuzz>=3.0.0
Provides-Extra: dev
Requires-Dist: pytest>=7.0.0; extra == "dev"
Requires-Dist: black>=23.0.0; extra == "dev"
Requires-Dist: ruff>=0.1.0; extra == "dev"
Requires-Dist: mypy>=1.0.0; extra == "dev"
Dynamic: license-file
